{
  "id": "LThVFg2aFviak8Ranf8nNX4UAEtLyzhyCNY2AQdXbgYkJdQTM",
  "name": "Rymedi Transaction",
  "description": "Rymedi's Connected Health Platform employs a unique double-helix blockchain design for enhanced data privacy and integrity in healthcare. It simplifies complex data integration across systems, ensuring compliance and offering adaptable workflows for seamless health record transfers. The platform emphasizes automated privacy, security, and efficient state reporting. Developed in partnership with regulatory bodies, Rymedi sets the standard for trustworthy, interoperable healthcare data solutions",
  "icon": "https://cdn.snowpeer.io/rymedi.svg",
  "color": "#524493",
  "website": "https://rymedi.com",
  "chains": [],
  "categories": [
    "HEALTH"
  ],
  "docs": "",
  "explorer": "",
  "socials": [
    {
      "name": "",
      "url": ""
    }
  ],
  "mainCategory": "",
  "assets": [
    {
      "for": "",
      "pricingDataProvider": [
        {
          "name": "",
          "id": ""
        }
      ],
      "symbol": "",
      "name": ""
    }
  ]
}