{
  "id": "7e3ziXMNuq29Y6nBBvWQZYAWYKyvhN5bhvmoNquNEbvFR51ad",
  "name": "Turf",
  "description": "TURF is an intent-driven data orchestration protocol that powers on-demand access to structured, high-context data. We intelligently route requests to relevant sources—bringing real-time, semantically aligned data to the agents and models that need it.",
  "mainCategory": "DATA",
  "primaryColor": "#c6fe20",
  "categories": ["DATA"],
  "links": {
    "website": "https://turf.network"
  },
  "chains": [
    {
      "id": "2bDPqb1bsLWxAjJ6WhZA5zNxPaurWHJvQynuzD6CnM8jieAvGS",
      "name": "TurfNetwork",
      "evmId": 62334
    }
  ]
}
